codetrail/__init__.py
codetrail/__main__.py
codetrail/cli.py
codetrail/cmd_config.py
codetrail/cmd_init.py
codetrail/commands.py
codetrail/conf.py
codetrail/exceptions.py
codetrail/models.py
codetrail/parsers.py
codetrail/utils.py
codetrail-0.4.0.dist-info/LICENSE
codetrail-0.4.0.dist-info/METADATA
codetrail-0.4.0.dist-info/WHEEL
codetrail-0.4.0.dist-info/entry_points.txt
codetrail-0.4.0.dist-info/RECORD
