Metadata-Version: 2.1
Name: codetrail
Version: 0.4.0
Summary: VCS inspired by Git.
Home-page: https://github.com/mochams/codetrail
Author: Mochama
Author-email: mochama254@protonmail.com
Requires-Python: >=3.12,<4.0
Classifier: Programming Language :: Python :: 3
Classifier: Programming Language :: Python :: 3.12
Classifier: Programming Language :: Python :: 3.13
Requires-Dist: pydantic (>=2.10.4,<3.0.0)
